qifqif/__init__.py
qifqif/config.py
qifqif/qifacc.py
qifqif/qifile.py
qifqif/tags.py
qifqif/terminal.py
qifqif/ui.py
qifqif-0.8.0.dist-info/LICENSE
qifqif-0.8.0.dist-info/METADATA
qifqif-0.8.0.dist-info/WHEEL
qifqif-0.8.0.dist-info/entry_points.txt
qifqif-0.8.0.dist-info/top_level.txt
qifqif-0.8.0.dist-info/RECORD
