Metadata-Version: 2.1
Name: qifqif
Version: 0.8.0
Summary: Enrich your QIF files with categories
Home-page: https://github.com/KraYmer/qifqif
Author: Fabrice Laporte
Author-email: kraymer@gmail.com
License: MIT
Platform: ALL
Classifier: License :: OSI Approved :: MIT License
Classifier: Programming Language :: Python
Classifier: Environment :: Console
Classifier: Topic :: Office/Business :: Financial :: Accounting
Requires-Dist: argparse
Requires-Dist: blessed (>=1.16)
Requires-Dist: coveralls
Requires-Dist: mock
Requires-Dist: ordereddict
Requires-Dist: prompt-toolkit (<3,>=2)
Requires-Dist: pyyaml
Requires-Dist: six
Requires-Dist: tox
